fileextract/Controller.py
fileextract/__init__.py
fileextract/__main__.py
fileextract/cmd/TSKCommand.py
fileextract/cmd/__init__.py
fileextract/processor/Processor.py
fileextract/processor/__init__.py
fileextract-1.0.0.dist-info/LICENSE.md
fileextract-1.0.0.dist-info/METADATA
fileextract-1.0.0.dist-info/WHEEL
fileextract-1.0.0.dist-info/entry_points.txt
fileextract-1.0.0.dist-info/top_level.txt
fileextract-1.0.0.dist-info/RECORD
