Metadata-Version: 2.1
Name: fileextract
Version: 1.0.0
Summary: Extracts files from .raw/.dd images using sleuthkit
Home-page: https://github.com/5f0ne/fileextract
Author: 5f0
License: MIT
Classifier: Operating System :: OS Independent 
Classifier: Programming Language :: Python :: 3 
Classifier: License :: OSI Approved :: MIT License 
License-File: LICENSE.md
